{"dependencies":[{"name":"./styles.css","dynamic":true},{"name":"./animations.js","dynamic":true},{"name":"./index.js","dynamic":true}],"generated":{"html":"<!DOCTYPE html>\r\n<html>\r\n<head>\r\n    <meta charset=\"utf-8\">\r\n    <meta http-equiv=\"X-UA-Compatible\" content=\"IE=edge\">\r\n    <title>Mobius ML</title>\r\n    <meta name=\"viewport\" content=\"width=device-width, initial-scale=1\">\r\n    <link rel=\"stylesheet\" href=\"https://fonts.googleapis.com/icon?family=Material+Icons\">\r\n    <link rel=\"stylesheet\" type=\"text/css\" media=\"screen\" href=\"/styles.67fbc3de.css\">\r\n    <link rel=\"stylesheet\" href=\"/styles.67fbc3de.css\">\r\n</head>\r\n<body style=\"width: 100%; height: 100%;\">\r\n    <div style=\"display: flex; flex-direction: row; align-items: center;\">\r\n        <h1>Mobius ML</h1>\r\n        <h2>Facial Recognition using Neural Networks</h2>\r\n    </div> \r\n    <div class=\"content\">\r\n        <div class=\"settings\">\r\n            <div class=\"buttons\">\r\n                <button id=\"train\" class=\"button\">Train</button>\r\n                <button id=\"predict\" class=\"button\">Run</button>\r\n                <button id=\"saveModel\" class=\"button\">Save</button>\r\n            </div>\r\n            <div id=\"status\">Loading mobilenet...</div>\r\n            <h2 id=\"train-status\"></h2>\r\n            <div class=\"hyper-params\">\r\n\r\n                <!-- Learning rate -->\r\n                <div class=\"dropdown\">\r\n                    <label>Learning rate</label>\r\n                    <select id=\"learningRate\" class=\"select\">\r\n                        <option value=\"0.00001\">0.00001</option>\r\n                        <option selected=\"\" value=\"0.0001\">0.0001</option>\r\n                        <option value=\"0.01\">0.001</option>\r\n                        <option value=\"0.03\">0.003</option>\r\n                    </select>\r\n                </div>\r\n        \r\n                <!-- Batch size -->\r\n                <div class=\"dropdown\">\r\n                    <label>Batch size</label>\r\n                    <select id=\"batchSizeFraction\" class=\"select\">\r\n                        <option value=\"0.05\">0.05</option>\r\n                        <option value=\"0.1\">0.1</option>\r\n                        <option selected=\"\" value=\"0.4\">0.4</option>\r\n                        <option value=\"1\">1</option>\r\n                    </select>\r\n                </div>\r\n        \r\n                <!-- Epochs -->\r\n                <div class=\"dropdown\">\r\n                    <label>Epochs</label>\r\n                    <select id=\"epochs\" class=\"select\">\r\n                        <option value=\"10\">10</option>\r\n                        <option selected=\"\" value=\"20\">20</option>\r\n                        <option value=\"40\">40</option>\r\n                    </select>\r\n                </div>\r\n        \r\n                <!-- Hidden units -->\r\n                <div class=\"dropdown\">\r\n                    <label>Hidden units</label>\r\n                    <select id=\"dense-units\" class=\"select\">\r\n                        <option value=\"10\">10</option>\r\n                        <option selected=\"\" value=\"100\">100</option>\r\n                        <option value=\"200\">200</option>\r\n                    </select>\r\n                </div>\r\n            \r\n            </div>\r\n        </div>\r\n        \r\n        <div class=\"circles\">\r\n            <div class=\"cam-circle\" id=\"top-camera\">\r\n                <button id=\"up\">\r\n                    <canvas class=\"thumb\" width=\"224\" height=\"224\" id=\"front-thumb\"></canvas>  \r\n                </button>\r\n            </div>\r\n            <div class=\"cam-circle\" id=\"bottom-camera\">\r\n                <button id=\"down\" on=\"\">\r\n                    <canvas class=\"thumb\" width=\"224\" height=\"224\" id=\"back-thumb\"></canvas>\r\n                </button>\r\n            </div>\r\n            <div class=\"cam-circle\" id=\"left-camera\">\r\n                <button id=\"left\">\r\n                    <canvas class=\"thumb\" width=\"224\" height=\"224\" id=\"left-thumb\"></canvas>\r\n                </button>\r\n            </div>\r\n            <div class=\"cam-circle\" id=\"right-camera\">\r\n                <button id=\"right\">\r\n                    <canvas class=\"thumb\" width=\"224\" height=\"224\" id=\"right-thumb\"></canvas>\r\n                </button>\r\n            </div>\r\n            <div class=\"cam-circle main\" id=\"camera\">\r\n                <button id=\"idle\">\r\n                    <div class=\"webcam-wrapper\">\r\n                        <video autoplay=\"\" playsinline=\"\" muted=\"\" id=\"webcam\" height=\"224\"></video>\r\n                    </div>\r\n                </button>\r\n            </div>\r\n        </div>\r\n    </div>\r\n\r\n    <script src=\"/animations.16340ec8.js\"></script>\r\n    <script src=\"/CongressionApp2018.c54a453b.js\"></script>\r\n</body>\r\n</html>"},"hash":"428a865fe64675a286457e646e070c79","cacheData":{}}